optconstruct/__init__.py
optconstruct/optionabstract.py
optconstruct/types/__init__.py
optconstruct/types/argument.py
optconstruct/types/basiccomposed.py
optconstruct/types/dummy.py
optconstruct/types/kwoption.py
optconstruct/types/listoption.py
optconstruct/types/prefixed.py
optconstruct/types/toggle.py
optconstruct-0.1.7.dist-info/DESCRIPTION.rst
optconstruct-0.1.7.dist-info/METADATA
optconstruct-0.1.7.dist-info/RECORD
optconstruct-0.1.7.dist-info/WHEEL
optconstruct-0.1.7.dist-info/entry_points.txt
optconstruct-0.1.7.dist-info/metadata.json
optconstruct-0.1.7.dist-info/top_level.txt
