Metadata-Version: 2.0
Name: optconstruct
Version: 0.1.7
Summary: This package provides an API for create appropriate option for command to execute in your application. API is called by one of several classes, which each of them handle different type of option.
Home-page: https://github.com/Frawless/optconstruct
Author: Dominik Lenoch <dlenoch@redhat.com>, Jakub Stejskal <jstejska@redhat.com>, Zdenek Kraus <zkraus@redhat.com>
Author-email: jstejska@redhat.com
License: Apache 2.0
Platform: UNKNOWN
Requires-Dist: reformat
